Metadata-Version: 2.1
Name: cppimport
Version: 22.8.2
Summary: Import C++ files directly from Python!
Home-page: https://github.com/tbenthompson/cppimport
Author: T. Ben Thompson
Author-email: t.ben.thompson@gmail.com
License: MIT
Platform: any
Classifier: Development Status :: 5 - Production/Stable
Classifier: Intended Audience :: Developers
Classifier: Operating System :: OS Independent
Classifier: Operating System :: POSIX
Classifier: Topic :: Software Development
Classifier: License :: OSI Approved :: MIT License
Classifier: Programming Language :: Python :: 3
Classifier: Programming Language :: C++
